Workbook

Sheet College Dashboard
B1: College Major ROI Dashboard
B2: 30,000 graduates | ROI = 10-yr added earnings - net cost | source: college_major_roi_cleaned.csv (via College_Data)
B3: FILTERS (pick from the yellow dropdowns; "All" = no filter) | D3: criteria (helper)
B4: Category | C4: All | D4: =IF(C4="All","*",C4) -> *
B5: Institution tier | C5: All | D5: =IF(C5="All","*",C5) -> *
B6: Region | C6: All | D6: =IF(C6="All","*",C6) -> *
B7: Internship | C7: All | D7: =IF(C7="All","*",C7) -> *
B8: On-time graduation | C8: All | D8: =IF(C8="All","*",C8) -> *
B10: GRADUATES | C10: AVG NET ROI | D10: % POSITIVE ROI | E10: % TOP-QUARTILE ROI | F10: AVG NET COST | G10: AVG DEBT
B11: =SUMIFS(College_Data!$G$2:$G$1515,College_Data!$B$2:$B$1515,$D$4,College_Data!$C$2:$C$1515,$D$5,College_Data!$D$2:$D$1515,$D$6,College_Data!$E$2:$E$1515,$D$7,College_Data!$F$2:$F$1515,$D$8) -> 30000 | C11: =IFERROR(SUMIFS(College_Data!$K$2:$K$1515,College_Data!$B$2:$B$1515,$D$4,College_Data!$C$2:$C$1515,$D$5,College_Data!$D$2:$D$1515,$D$6,College_Data!$E$2:$E$1515,$D$7,College_Data!$F$2:$F$1515,$D$8)/SUMIFS(College_Data!$G$2:$G$1515,College_Data!$B$2:$B$1515,$D$4,College_Data!$C$2:$C$1515,$D$5,College_Data!$D$2:$D$1515,$D$6,College_Data!$E$2:$E$1515,$D$7,College_Data!$F$2:$F$1515,$D$8),0) -> 266853.72 | D11: =IFERROR(SUMIFS(College_Data!$L$2:$L$1515,College_Data!$B$2:$B$1515,$D$4,College_Data!$C$2:$C$1515,$D$5,College_Data!$D$2:$D$1515,$D$6,College_Data!$E$2:$E$1515,$D$7,College_Data!$F$2:$F$1515,$D$8)/SUMIFS(College_Data!$G$2:$G$1515,College_Data!$B$2:$B$1515,$D$4,College_Data!$C$2:$C$1515,$D$5,College_Data!$D$2:$D$1515,$D$6,College_Data!$E$2:$E$1515,$D$7,College_Data!$F$2:$F$1515,$D$8),0) -> 0.83516667 | E11: =IFERROR(SUMIFS(College_Data!$M$2:$M$1515,College_Data!$B$2:$B$1515,$D$4,College_Data!$C$2:$C$1515,$D$5,College_Data!$D$2:$D$1515,$D$6,College_Data!$E$2:$E$1515,$D$7,College_Data!$F$2:$F$1515,$D$8)/SUMIFS(College_Data!$G$2:$G$1515,College_Data!$B$2:$B$1515,$D$4,College_Data!$C$2:$C$1515,$D$5,College_Data!$D$2:$D$1515,$D$6,College_Data!$E$2:$E$1515,$D$7,College_Data!$F$2:$F$1515,$D$8),0) -> 0.25 | F11: =IFERROR(SUMIFS(College_Data!$H$2:$H$1515,College_Data!$B$2:$B$1515,$D$4,College_Data!$C$2:$C$1515,$D$5,College_Data!$D$2:$D$1515,$D$6,College_Data!$E$2:$E$1515,$D$7,College_Data!$F$2:$F$1515,$D$8)/SUMIFS(College_Data!$G$2:$G$1515,College_Data!$B$2:$B$1515,$D$4,College_Data!$C$2:$C$1515,$D$5,College_Data!$D$2:$D$1515,$D$6,College_Data!$E$2:$E$1515,$D$7,College_Data!$F$2:$F$1515,$D$8),0) -> 88621.497 | G11: =IFERROR(SUMIFS(College_Data!$I$2:$I$1515,College_Data!$B$2:$B$1515,$D$4,College_Data!$C$2:$C$1515,$D$5,College_Data!$D$2:$D$1515,$D$6,College_Data!$E$2:$E$1515,$D$7,College_Data!$F$2:$F$1515,$D$8)/SUMIFS(College_Data!$G$2:$G$1515,College_Data!$B$2:$B$1515,$D$4,College_Data!$C$2:$C$1515,$D$5,College_Data!$D$2:$D$1515,$D$6,College_Data!$E$2:$E$1515,$D$7,College_Data!$F$2:$F$1515,$D$8),0) -> 38498.063
B13: Outcomes by major
B14: Major | C14: Category | D14: Graduates | E14: Avg net ROI | F14: % positive ROI | G14: Avg net cost | H14: Avg debt
B15: electrical_engineering | C15: STEM | D15: =SUMIFS(College_Data!$G$2:$G$1515,College_Data!$A$2:$A$1515,$B15,College_Data!$B$2:$B$1515,$D$4,College_Data!$C$2:$C$1515,$D$5,College_Data!$D$2:$D$1515,$D$6,College_Data!$E$2:$E$1515,$D$7,College_Data!$F$2:$F$1515,$D$8) -> 1621 | E15: =IFERROR(SUMIFS(College_Data!$K$2:$K$1515,College_Data!$A$2:$A$1515,$B15,College_Data!$B$2:$B$1515,$D$4,College_Data!$C$2:$C$1515,$D$5,College_Data!$D$2:$D$1515,$D$6,College_Data!$E$2:$E$1515,$D$7,College_Data!$F$2:$F$1515,$D$8)/D15,0) -> 600364.53 | F15: =IFERROR(SUMIFS(College_Data!$L$2:$L$1515,College_Data!$A$2:$A$1515,$B15,College_Data!$B$2:$B$1515,$D$4,College_Data!$C$2:$C$1515,$D$5,College_Data!$D$2:$D$1515,$D$6,College_Data!$E$2:$E$1515,$D$7,College_Data!$F$2:$F$1515,$D$8)/D15,0) -> 0.9993831 | G15: =IFERROR(SUMIFS(College_Data!$H$2:$H$1515,College_Data!$A$2:$A$1515,$B15,College_Data!$B$2:$B$1515,$D$4,College_Data!$C$2:$C$1515,$D$5,College_Data!$D$2:$D$1515,$D$6,College_Data!$E$2:$E$1515,$D$7,College_Data!$F$2:$F$1515,$D$8)/D15,0) -> 90013.14 | H15: =IFERROR(SUMIFS(College_Data!$I$2:$I$1515,College_Data!$A$2:$A$1515,$B15,College_Data!$B$2:$B$1515,$D$4,College_Data!$C$2:$C$1515,$D$5,College_Data!$D$2:$D$1515,$D$6,College_Data!$E$2:$E$1515,$D$7,College_Data!$F$2:$F$1515,$D$8)/D15,0) -> 39846.885
B16: business_analytics | C16: business | D16: =SUMIFS(College_Data!$G$2:$G$1515,College_Data!$A$2:$A$1515,$B16,College_Data!$B$2:$B$1515,$D$4,College_Data!$C$2:$C$1515,$D$5,College_Data!$D$2:$D$1515,$D$6,College_Data!$E$2:$E$1515,$D$7,College_Data!$F$2:$F$1515,$D$8) -> 1708 | E16: =IFERROR(SUMIFS(College_Data!$K$2:$K$1515,College_Data!$A$2:$A$1515,$B16,College_Data!$B$2:$B$1515,$D$4,College_Data!$C$2:$C$1515,$D$5,College_Data!$D$2:$D$1515,$D$6,College_Data!$E$2:$E$1515,$D$7,College_Data!$F$2:$F$1515,$D$8)/D16,0) -> 525387.53 | F16: =IFERROR(SUMIFS(College_Data!$L$2:$L$1515,College_Data!$A$2:$A$1515,$B16,College_Data!$B$2:$B$1515,$D$4,College_Data!$C$2:$C$1515,$D$5,College_Data!$D$2:$D$1515,$D$6,College_Data!$E$2:$E$1515,$D$7,College_Data!$F$2:$F$1515,$D$8)/D16,0) -> 1 | G16: =IFERROR(SUMIFS(College_Data!$H$2:$H$1515,College_Data!$A$2:$A$1515,$B16,College_Data!$B$2:$B$1515,$D$4,College_Data!$C$2:$C$1515,$D$5,College_Data!$D$2:$D$1515,$D$6,College_Data!$E$2:$E$1515,$D$7,College_Data!$F$2:$F$1515,$D$8)/D16,0) -> 88229.625 | H16: =IFERROR(SUMIFS(College_Data!$I$2:$I$1515,College_Data!$A$2:$A$1515,$B16,College_Data!$B$2:$B$1515,$D$4,College_Data!$C$2:$C$1515,$D$5,College_Data!$D$2:$D$1515,$D$6,College_Data!$E$2:$E$1515,$D$7,College_Data!$F$2:$F$1515,$D$8)/D16,0) -> 39162.998
B17: chemical_engineering | C17: STEM | D17: =SUMIFS(College_Data!$G$2:$G$1515,College_Data!$A$2:$A$1515,$B17,College_Data!$B$2:$B$1515,$D$4,College_Data!$C$2:$C$1515,$D$5,College_Data!$D$2:$D$1515,$D$6,College_Data!$E$2:$E$1515,$D$7,College_Data!$F$2:$F$1515,$D$8) -> 1626 | E17: =IFERROR(SUMIFS(College_Data!$K$2:$K$1515,College_Data!$A$2:$A$1515,$B17,College_Data!$B$2:$B$1515,$D$4,College_Data!$C$2:$C$1515,$D$5,College_Data!$D$2:$D$1515,$D$6,College_Data!$E$2:$E$1515,$D$7,College_Data!$F$2:$F$1515,$D$8)/D17,0) -> 523859.72 | F17: =IFERROR(SUMIFS(College_Data!$L$2:$L$1515,College_Data!$A$2:$A$1515,$B17,College_Data!$B$2:$B$1515,$D$4,College_Data!$C$2:$C$1515,$D$5,College_Data!$D$2:$D$1515,$D$6,College_Data!$E$2:$E$1515,$D$7,College_Data!$F$2:$F$1515,$D$8)/D17,0) -> 0.99692497 | G17: =IFERROR(SUMIFS(College_Data!$H$2:$H$1515,College_Data!$A$2:$A$1515,$B17,College_Data!$B$2:$B$1515,$D$4,College_Data!$C$2:$C$1515,$D$5,College_Data!$D$2:$D$1515,$D$6,College_Data!$E$2:$E$1515,$D$7,College_Data!$F$2:$F$1515,$D$8)/D17,0) -> 88598.893 | H17: =IFERROR(SUMIFS(College_Data!$I$2:$I$1515,College_Data!$A$2:$A$1515,$B17,College_Data!$B$2:$B$1515,$D$4,College_Data!$C$2:$C$1515,$D$5,College_Data!$D$2:$D$1515,$D$6,College_Data!$E$2:$E$1515,$D$7,College_Data!$F$2:$F$1515,$D$8)/D17,0) -> 39077.06
B18: computer_science | C18: STEM | D18: =SUMIFS(College_Data!$G$2:$G$1515,College_Data!$A$2:$A$1515,$B18,College_Data!$B$2:$B$1515,$D$4,College_Data!$C$2:$C$1515,$D$5,College_Data!$D$2:$D$1515,$D$6,College_Data!$E$2:$E$1515,$D$7,College_Data!$F$2:$F$1515,$D$8) -> 1628 | E18: =IFERROR(SUMIFS(College_Data!$K$2:$K$1515,College_Data!$A$2:$A$1515,$B18,College_Data!$B$2:$B$1515,$D$4,College_Data!$C$2:$C$1515,$D$5,College_Data!$D$2:$D$1515,$D$6,College_Data!$E$2:$E$1515,$D$7,College_Data!$F$2:$F$1515,$D$8)/D18,0) -> 517457.62 | F18: =IFERROR(SUMIFS(College_Data!$L$2:$L$1515,College_Data!$A$2:$A$1515,$B18,College_Data!$B$2:$B$1515,$D$4,College_Data!$C$2:$C$1515,$D$5,College_Data!$D$2:$D$1515,$D$6,College_Data!$E$2:$E$1515,$D$7,College_Data!$F$2:$F$1515,$D$8)/D18,0) -> 0.997543 | G18: =IFERROR(SUMIFS(College_Data!$H$2:$H$1515,College_Data!$A$2:$A$1515,$B18,College_Data!$B$2:$B$1515,$D$4,College_Data!$C$2:$C$1515,$D$5,College_Data!$D$2:$D$1515,$D$6,College_Data!$E$2:$E$1515,$D$7,College_Data!$F$2:$F$1515,$D$8)/D18,0) -> 88997.052 | H18: =IFERROR(SUMIFS(College_Data!$I$2:$I$1515,College_Data!$A$2:$A$1515,$B18,College_Data!$B$2:$B$1515,$D$4,College_Data!$C$2:$C$1515,$D$5,College_Data!$D$2:$D$1515,$D$6,College_Data!$E$2:$E$1515,$D$7,College_Data!$F$2:$F$1515,$D$8)/D18,0) -> 37873.833
B19: computer_engineering | C19: STEM | D19: =SUMIFS(College_Data!$G$2:$G$1515,College_Data!$A$2:$A$1515,$B19,College_Data!$B$2:$B$1515,$D$4,College_Data!$C$2:$C$1515,$D$5,College_Data!$D$2:$D$1515,$D$6,College_Data!$E$2:$E$1515,$D$7,College_Data!$F$2:$F$1515,$D$8) -> 1659 | E19: =IFERROR(SUMIFS(College_Data!$K$2:$K$1515,College_Data!$A$2:$A$1515,$B19,College_Data!$B$2:$B$1515,$D$4,College_Data!$C$2:$C$1515,$D$5,College_Data!$D$2:$D$1515,$D$6,College_Data!$E$2:$E$1515,$D$7,College_Data!$F$2:$F$1515,$D$8)/D19,0) -> 495987.52 | F19: =IFERROR(SUMIFS(College_Data!$L$2:$L$1515,College_Data!$A$2:$A$1515,$B19,College_Data!$B$2:$B$1515,$D$4,College_Data!$C$2:$C$1515,$D$5,College_Data!$D$2:$D$1515,$D$6,College_Data!$E$2:$E$1515,$D$7,College_Data!$F$2:$F$1515,$D$8)/D19,0) -> 0.99939723 | G19: =IFERROR(SUMIFS(College_Data!$H$2:$H$1515,College_Data!$A$2:$A$1515,$B19,College_Data!$B$2:$B$1515,$D$4,College_Data!$C$2:$C$1515,$D$5,College_Data!$D$2:$D$1515,$D$6,College_Data!$E$2:$E$1515,$D$7,College_Data!$F$2:$F$1515,$D$8)/D19,0) -> 87920.072 | H19: =IFERROR(SUMIFS(College_Data!$I$2:$I$1515,College_Data!$A$2:$A$1515,$B19,College_Data!$B$2:$B$1515,$D$4,College_Data!$C$2:$C$1515,$D$5,College_Data!$D$2:$D$1515,$D$6,College_Data!$E$2:$E$1515,$D$7,College_Data!$F$2:$F$1515,$D$8)/D19,0) -> 38272.453
B20: economics | C20: business | D20: =SUMIFS(College_Data!$G$2:$G$1515,College_Data!$A$2:$A$1515,$B20,College_Data!$B$2:$B$1515,$D$4,College_Data!$C$2:$C$1515,$D$5,College_Data!$D$2:$D$1515,$D$6,College_Data!$E$2:$E$1515,$D$7,College_Data!$F$2:$F$1515,$D$8) -> 1580 | E20: =IFERROR(SUMIFS(College_Data!$K$2:$K$1515,College_Data!$A$2:$A$1515,$B20,College_Data!$B$2:$B$1515,$D$4,College_Data!$C$2:$C$1515,$D$5,College_Data!$D$2:$D$1515,$D$6,College_Data!$E$2:$E$1515,$D$7,College_Data!$F$2:$F$1515,$D$8)/D20,0) -> 445033.1 | F20: =IFERROR(SUMIFS(College_Data!$L$2:$L$1515,College_Data!$A$2:$A$1515,$B20,College_Data!$B$2:$B$1515,$D$4,College_Data!$C$2:$C$1515,$D$5,College_Data!$D$2:$D$1515,$D$6,College_Data!$E$2:$E$1515,$D$7,College_Data!$F$2:$F$1515,$D$8)/D20,0) -> 0.99746835 | G20: =IFERROR(SUMIFS(College_Data!$H$2:$H$1515,College_Data!$A$2:$A$1515,$B20,College_Data!$B$2:$B$1515,$D$4,College_Data!$C$2:$C$1515,$D$5,College_Data!$D$2:$D$1515,$D$6,College_Data!$E$2:$E$1515,$D$7,College_Data!$F$2:$F$1515,$D$8)/D20,0) -> 89375.316 | H20: =IFERROR(SUMIFS(College_Data!$I$2:$I$1515,College_Data!$A$2:$A$1515,$B20,College_Data!$B$2:$B$1515,$D$4,College_Data!$C$2:$C$1515,$D$5,College_Data!$D$2:$D$1515,$D$6,College_Data!$E$2:$E$1515,$D$7,College_Data!$F$2:$F$1515,$D$8)/D20,0) -> 37990.253
B21: mechanical_engineering | C21: STEM | D21: =SUMIFS(College_Data!$G$2:$G$1515,College_Data!$A$2:$A$1515,$B21,College_Data!$B$2:$B$1515,$D$4,College_Data!$C$2:$C$1515,$D$5,College_Data!$D$2:$D$1515,$D$6,College_Data!$E$2:$E$1515,$D$7,College_Data!$F$2:$F$1515,$D$8) -> 1635 | E21: =IFERROR(SUMIFS(College_Data!$K$2:$K$1515,College_Data!$A$2:$A$1515,$B21,College_Data!$B$2:$B$1515,$D$4,College_Data!$C$2:$C$1515,$D$5,College_Data!$D$2:$D$1515,$D$6,College_Data!$E$2:$E$1515,$D$7,College_Data!$F$2:$F$1515,$D$8)/D21,0) -> 427708.26 | F21: =IFERROR(SUMIFS(College_Data!$L$2:$L$1515,College_Data!$A$2:$A$1515,$B21,College_Data!$B$2:$B$1515,$D$4,College_Data!$C$2:$C$1515,$D$5,College_Data!$D$2:$D$1515,$D$6,College_Data!$E$2:$E$1515,$D$7,College_Data!$F$2:$F$1515,$D$8)/D21,0) -> 0.9969419 | G21: =IFERROR(SUMIFS(College_Data!$H$2:$H$1515,College_Data!$A$2:$A$1515,$B21,College_Data!$B$2:$B$1515,$D$4,College_Data!$C$2:$C$1515,$D$5,College_Data!$D$2:$D$1515,$D$6,College_Data!$E$2:$E$1515,$D$7,College_Data!$F$2:$F$1515,$D$8)/D21,0) -> 87814.924 | H21: =IFERROR(SUMIFS(College_Data!$I$2:$I$1515,College_Data!$A$2:$A$1515,$B21,College_Data!$B$2:$B$1515,$D$4,College_Data!$C$2:$C$1515,$D$5,College_Data!$D$2:$D$1515,$D$6,College_Data!$E$2:$E$1515,$D$7,College_Data!$F$2:$F$1515,$D$8)/D21,0) -> 37899.388
B22: finance | C22: business | D22: =SUMIFS(College_Data!$G$2:$G$1515,College_Data!$A$2:$A$1515,$B22,College_Data!$B$2:$B$1515,$D$4,College_Data!$C$2:$C$1515,$D$5,College_Data!$D$2:$D$1515,$D$6,College_Data!$E$2:$E$1515,$D$7,College_Data!$F$2:$F$1515,$D$8) -> 1676 | E22: =IFERROR(SUMIFS(College_Data!$K$2:$K$1515,College_Data!$A$2:$A$1515,$B22,College_Data!$B$2:$B$1515,$D$4,College_Data!$C$2:$C$1515,$D$5,College_Data!$D$2:$D$1515,$D$6,College_Data!$E$2:$E$1515,$D$7,College_Data!$F$2:$F$1515,$D$8)/D22,0) -> 351285.14 | F22: =IFERROR(SUMIFS(College_Data!$L$2:$L$1515,College_Data!$A$2:$A$1515,$B22,College_Data!$B$2:$B$1515,$D$4,College_Data!$C$2:$C$1515,$D$5,College_Data!$D$2:$D$1515,$D$6,College_Data!$E$2:$E$1515,$D$7,College_Data!$F$2:$F$1515,$D$8)/D22,0) -> 0.99403341 | G22: =IFERROR(SUMIFS(College_Data!$H$2:$H$1515,College_Data!$A$2:$A$1515,$B22,College_Data!$B$2:$B$1515,$D$4,College_Data!$C$2:$C$1515,$D$5,College_Data!$D$2:$D$1515,$D$6,College_Data!$E$2:$E$1515,$D$7,College_Data!$F$2:$F$1515,$D$8)/D22,0) -> 87432.995 | H22: =IFERROR(SUMIFS(College_Data!$I$2:$I$1515,College_Data!$A$2:$A$1515,$B22,College_Data!$B$2:$B$1515,$D$4,College_Data!$C$2:$C$1515,$D$5,College_Data!$D$2:$D$1515,$D$6,College_Data!$E$2:$E$1515,$D$7,College_Data!$F$2:$F$1515,$D$8)/D22,0) -> 38454.654
B23: nursing | C23: health | D23: =SUMIFS(College_Data!$G$2:$G$1515,College_Data!$A$2:$A$1515,$B23,College_Data!$B$2:$B$1515,$D$4,College_Data!$C$2:$C$1515,$D$5,College_Data!$D$2:$D$1515,$D$6,College_Data!$E$2:$E$1515,$D$7,College_Data!$F$2:$F$1515,$D$8) -> 1589 | E23: =IFERROR(SUMIFS(College_Data!$K$2:$K$1515,College_Data!$A$2:$A$1515,$B23,College_Data!$B$2:$B$1515,$D$4,College_Data!$C$2:$C$1515,$D$5,College_Data!$D$2:$D$1515,$D$6,College_Data!$E$2:$E$1515,$D$7,College_Data!$F$2:$F$1515,$D$8)/D23,0) -> 350828.82 | F23: =IFERROR(SUMIFS(College_Data!$L$2:$L$1515,College_Data!$A$2:$A$1515,$B23,College_Data!$B$2:$B$1515,$D$4,College_Data!$C$2:$C$1515,$D$5,College_Data!$D$2:$D$1515,$D$6,College_Data!$E$2:$E$1515,$D$7,College_Data!$F$2:$F$1515,$D$8)/D23,0) -> 0.99181875 | G23: =IFERROR(SUMIFS(College_Data!$H$2:$H$1515,College_Data!$A$2:$A$1515,$B23,College_Data!$B$2:$B$1515,$D$4,College_Data!$C$2:$C$1515,$D$5,College_Data!$D$2:$D$1515,$D$6,College_Data!$E$2:$E$1515,$D$7,College_Data!$F$2:$F$1515,$D$8)/D23,0) -> 89831.844 | H23: =IFERROR(SUMIFS(College_Data!$I$2:$I$1515,College_Data!$A$2:$A$1515,$B23,College_Data!$B$2:$B$1515,$D$4,College_Data!$C$2:$C$1515,$D$5,College_Data!$D$2:$D$1515,$D$6,College_Data!$E$2:$E$1515,$D$7,College_Data!$F$2:$F$1515,$D$8)/D23,0) -> 39586.029
B24: business | C24: business | D24: =SUMIFS(College_Data!$G$2:$G$1515,College_Data!$A$2:$A$1515,$B24,College_Data!$B$2:$B$1515,$D$4,College_Data!$C$2:$C$1515,$D$5,College_Data!$D$2:$D$1515,$D$6,College_Data!$E$2:$E$1515,$D$7,College_Data!$F$2:$F$1515,$D$8) -> 1694 | E24: =IFERROR(SUMIFS(College_Data!$K$2:$K$1515,College_Data!$A$2:$A$1515,$B24,College_Data!$B$2:$B$1515,$D$4,College_Data!$C$2:$C$1515,$D$5,College_Data!$D$2:$D$1515,$D$6,College_Data!$E$2:$E$1515,$D$7,College_Data!$F$2:$F$1515,$D$8)/D24,0) -> 269915.41 | F24: =IFERROR(SUMIFS(College_Data!$L$2:$L$1515,College_Data!$A$2:$A$1515,$B24,College_Data!$B$2:$B$1515,$D$4,College_Data!$C$2:$C$1515,$D$5,College_Data!$D$2:$D$1515,$D$6,College_Data!$E$2:$E$1515,$D$7,College_Data!$F$2:$F$1515,$D$8)/D24,0) -> 0.98229044 | G24: =IFERROR(SUMIFS(College_Data!$H$2:$H$1515,College_Data!$A$2:$A$1515,$B24,College_Data!$B$2:$B$1515,$D$4,College_Data!$C$2:$C$1515,$D$5,College_Data!$D$2:$D$1515,$D$6,College_Data!$E$2:$E$1515,$D$7,College_Data!$F$2:$F$1515,$D$8)/D24,0) -> 87600.354 | H24: =IFERROR(SUMIFS(College_Data!$I$2:$I$1515,College_Data!$A$2:$A$1515,$B24,College_Data!$B$2:$B$1515,$D$4,College_Data!$C$2:$C$1515,$D$5,College_Data!$D$2:$D$1515,$D$6,College_Data!$E$2:$E$1515,$D$7,College_Data!$F$2:$F$1515,$D$8)/D24,0) -> 36319.008
B25: marketing | C25: business | D25: =SUMIFS(College_Data!$G$2:$G$1515,College_Data!$A$2:$A$1515,$B25,College_Data!$B$2:$B$1515,$D$4,College_Data!$C$2:$C$1515,$D$5,College_Data!$D$2:$D$1515,$D$6,College_Data!$E$2:$E$1515,$D$7,College_Data!$F$2:$F$1515,$D$8) -> 1703 | E25: =IFERROR(SUMIFS(College_Data!$K$2:$K$1515,College_Data!$A$2:$A$1515,$B25,College_Data!$B$2:$B$1515,$D$4,College_Data!$C$2:$C$1515,$D$5,College_Data!$D$2:$D$1515,$D$6,College_Data!$E$2:$E$1515,$D$7,College_Data!$F$2:$F$1515,$D$8)/D25,0) -> 145174.4 | F25: =IFERROR(SUMIFS(College_Data!$L$2:$L$1515,College_Data!$A$2:$A$1515,$B25,College_Data!$B$2:$B$1515,$D$4,College_Data!$C$2:$C$1515,$D$5,College_Data!$D$2:$D$1515,$D$6,College_Data!$E$2:$E$1515,$D$7,College_Data!$F$2:$F$1515,$D$8)/D25,0) -> 0.94891368 | G25: =IFERROR(SUMIFS(College_Data!$H$2:$H$1515,College_Data!$A$2:$A$1515,$B25,College_Data!$B$2:$B$1515,$D$4,College_Data!$C$2:$C$1515,$D$5,College_Data!$D$2:$D$1515,$D$6,College_Data!$E$2:$E$1515,$D$7,College_Data!$F$2:$F$1515,$D$8)/D25,0) -> 88524.31 | H25: =IFERROR(SUMIFS(College_Data!$I$2:$I$1515,College_Data!$A$2:$A$1515,$B25,College_Data!$B$2:$B$1515,$D$4,College_Data!$C$2:$C$1515,$D$5,College_Data!$D$2:$D$1515,$D$6,College_Data!$E$2:$E$1515,$D$7,College_Data!$F$2:$F$1515,$D$8)/D25,0) -> 38433.294
B26: biology | C26: STEM | D26: =SUMIFS(College_Data!$G$2:$G$1515,College_Data!$A$2:$A$1515,$B26,College_Data!$B$2:$B$1515,$D$4,College_Data!$C$2:$C$1515,$D$5,College_Data!$D$2:$D$1515,$D$6,College_Data!$E$2:$E$1515,$D$7,College_Data!$F$2:$F$1515,$D$8) -> 1735 | E26: =IFERROR(SUMIFS(College_Data!$K$2:$K$1515,College_Data!$A$2:$A$1515,$B26,College_Data!$B$2:$B$1515,$D$4,College_Data!$C$2:$C$1515,$D$5,College_Data!$D$2:$D$1515,$D$6,College_Data!$E$2:$E$1515,$D$7,College_Data!$F$2:$F$1515,$D$8)/D26,0) -> 136905.99 | F26: =IFERROR(SUMIFS(College_Data!$L$2:$L$1515,College_Data!$A$2:$A$1515,$B26,College_Data!$B$2:$B$1515,$D$4,College_Data!$C$2:$C$1515,$D$5,College_Data!$D$2:$D$1515,$D$6,College_Data!$E$2:$E$1515,$D$7,College_Data!$F$2:$F$1515,$D$8)/D26,0) -> 0.93429395 | G26: =IFERROR(SUMIFS(College_Data!$H$2:$H$1515,College_Data!$A$2:$A$1515,$B26,College_Data!$B$2:$B$1515,$D$4,College_Data!$C$2:$C$1515,$D$5,College_Data!$D$2:$D$1515,$D$6,College_Data!$E$2:$E$1515,$D$7,College_Data!$F$2:$F$1515,$D$8)/D26,0) -> 88062.305 | H26: =IFERROR(SUMIFS(College_Data!$I$2:$I$1515,College_Data!$A$2:$A$1515,$B26,College_Data!$B$2:$B$1515,$D$4,College_Data!$C$2:$C$1515,$D$5,College_Data!$D$2:$D$1515,$D$6,College_Data!$E$2:$E$1515,$D$7,College_Data!$F$2:$F$1515,$D$8)/D26,0) -> 37736.945
... B33: fine_arts | C33: arts | D33: =SUMIFS(College_Data!$G$2:$G$1515,College_Data!$A$2:$A$1515,$B33,College_Data!$B$2:$B$1515,$D$4,College_Data!$C$2:$C$1515,$D$5,College_Data!$D$2:$D$1515,$D$6,College_Data!$E$2:$E$1515,$D$7,College_Data!$F$2:$F$1515,$D$8) -> 1395 | E33: =IFERROR(SUMIFS(College_Data!$K$2:$K$1515,College_Data!$A$2:$A$1515,$B33,College_Data!$B$2:$B$1515,$D$4,College_Data!$C$2:$C$1515,$D$5,College_Data!$D$2:$D$1515,$D$6,College_Data!$E$2:$E$1515,$D$7,College_Data!$F$2:$F$1515,$D$8)/D33,0) -> -39821.147 | F33: =IFERROR(SUMIFS(College_Data!$L$2:$L$1515,College_Data!$A$2:$A$1515,$B33,College_Data!$B$2:$B$1515,$D$4,College_Data!$C$2:$C$1515,$D$5,College_Data!$D$2:$D$1515,$D$6,College_Data!$E$2:$E$1515,$D$7,College_Data!$F$2:$F$1515,$D$8)/D33,0) -> 0.11111111 | G33: =IFERROR(SUMIFS(College_Data!$H$2:$H$1515,College_Data!$A$2:$A$1515,$B33,College_Data!$B$2:$B$1515,$D$4,College_Data!$C$2:$C$1515,$D$5,College_Data!$D$2:$D$1515,$D$6,College_Data!$E$2:$E$1515,$D$7,College_Data!$F$2:$F$1515,$D$8)/D33,0) -> 87935.341 | H33: =IFERROR(SUMIFS(College_Data!$I$2:$I$1515,College_Data!$A$2:$A$1515,$B33,College_Data!$B$2:$B$1515,$D$4,College_Data!$C$2:$C$1515,$D$5,College_Data!$D$2:$D$1515,$D$6,College_Data!$E$2:$E$1515,$D$7,College_Data!$F$2:$F$1515,$D$8)/D33,0) -> 38392.832
B36: By institution tier | J36: By major category
B37: Tier | C37: Graduates | D37: Avg net ROI | E37: % positive ROI | F37: Avg net cost | G37: Avg debt | H37: Avg added earnings | J37: Category | K37: Graduates | L37: Avg net ROI | M37: % positive ROI
B38: ivy_elite | C38: =SUMIFS(College_Data!$G$2:$G$1515,College_Data!$C$2:$C$1515,$B38,College_Data!$B$2:$B$1515,$D$4,College_Data!$D$2:$D$1515,$D$6,College_Data!$E$2:$E$1515,$D$7,College_Data!$F$2:$F$1515,$D$8) -> 1752 | D38: =IFERROR(SUMIFS(College_Data!$K$2:$K$1515,College_Data!$C$2:$C$1515,$B38,College_Data!$B$2:$B$1515,$D$4,College_Data!$D$2:$D$1515,$D$6,College_Data!$E$2:$E$1515,$D$7,College_Data!$F$2:$F$1515,$D$8)/C38,0) -> 380610.1 | E38: =IFERROR(SUMIFS(College_Data!$L$2:$L$1515,College_Data!$C$2:$C$1515,$B38,College_Data!$B$2:$B$1515,$D$4,College_Data!$D$2:$D$1515,$D$6,College_Data!$E$2:$E$1515,$D$7,College_Data!$F$2:$F$1515,$D$8)/C38,0) -> 0.79737443 | F38: =IFERROR(SUMIFS(College_Data!$H$2:$H$1515,College_Data!$C$2:$C$1515,$B38,College_Data!$B$2:$B$1515,$D$4,College_Data!$D$2:$D$1515,$D$6,College_Data!$E$2:$E$1515,$D$7,College_Data!$F$2:$F$1515,$D$8)/C38,0) -> 161819.01 | G38: =IFERROR(SUMIFS(College_Data!$I$2:$I$1515,College_Data!$C$2:$C$1515,$B38,College_Data!$B$2:$B$1515,$D$4,College_Data!$D$2:$D$1515,$D$6,College_Data!$E$2:$E$1515,$D$7,College_Data!$F$2:$F$1515,$D$8)/C38,0) -> 72744.349 | H38: =IFERROR(SUMIFS(College_Data!$J$2:$J$1515,College_Data!$C$2:$C$1515,$B38,College_Data!$B$2:$B$1515,$D$4,College_Data!$D$2:$D$1515,$D$6,College_Data!$E$2:$E$1515,$D$7,College_Data!$F$2:$F$1515,$D$8)/C38,0) -> 542429.22 | J38: STEM | K38: =SUMIFS(College_Data!$G$2:$G$1515,College_Data!$B$2:$B$1515,$J38,College_Data!$C$2:$C$1515,$D$5,College_Data!$D$2:$D$1515,$D$6,College_Data!$E$2:$E$1515,$D$7,College_Data!$F$2:$F$1515,$D$8) -> 9904 | L38: =IFERROR(SUMIFS(College_Data!$K$2:$K$1515,College_Data!$B$2:$B$1515,$J38,College_Data!$C$2:$C$1515,$D$5,College_Data!$D$2:$D$1515,$D$6,College_Data!$E$2:$E$1515,$D$7,College_Data!$F$2:$F$1515,$D$8)/K38,0) -> 446999.8 | M38: =IFERROR(SUMIFS(College_Data!$L$2:$L$1515,College_Data!$B$2:$B$1515,$J38,College_Data!$C$2:$C$1515,$D$5,College_Data!$D$2:$D$1515,$D$6,College_Data!$E$2:$E$1515,$D$7,College_Data!$F$2:$F$1515,$D$8)/K38,0) -> 0.98687399
B39: top_public | C39: =SUMIFS(College_Data!$G$2:$G$1515,College_Data!$C$2:$C$1515,$B39,College_Data!$B$2:$B$1515,$D$4,College_Data!$D$2:$D$1515,$D$6,College_Data!$E$2:$E$1515,$D$7,College_Data!$F$2:$F$1515,$D$8) -> 5996 | D39: =IFERROR(SUMIFS(College_Data!$K$2:$K$1515,College_Data!$C$2:$C$1515,$B39,College_Data!$B$2:$B$1515,$D$4,College_Data!$D$2:$D$1515,$D$6,College_Data!$E$2:$E$1515,$D$7,College_Data!$F$2:$F$1515,$D$8)/C39,0) -> 328414.68 | E39: =IFERROR(SUMIFS(College_Data!$L$2:$L$1515,College_Data!$C$2:$C$1515,$B39,College_Data!$B$2:$B$1515,$D$4,College_Data!$D$2:$D$1515,$D$6,College_Data!$E$2:$E$1515,$D$7,College_Data!$F$2:$F$1515,$D$8)/C39,0) -> 0.85607071 | F39: =IFERROR(SUMIFS(College_Data!$H$2:$H$1515,College_Data!$C$2:$C$1515,$B39,College_Data!$B$2:$B$1515,$D$4,College_Data!$D$2:$D$1515,$D$6,College_Data!$E$2:$E$1515,$D$7,College_Data!$F$2:$F$1515,$D$8)/C39,0) -> 94036.541 | G39: =IFERROR(SUMIFS(College_Data!$I$2:$I$1515,College_Data!$C$2:$C$1515,$B39,College_Data!$B$2:$B$1515,$D$4,College_Data!$D$2:$D$1515,$D$6,College_Data!$E$2:$E$1515,$D$7,College_Data!$F$2:$F$1515,$D$8)/C39,0) -> 40436.224 | H39: =IFERROR(SUMIFS(College_Data!$J$2:$J$1515,College_Data!$C$2:$C$1515,$B39,College_Data!$B$2:$B$1515,$D$4,College_Data!$D$2:$D$1515,$D$6,College_Data!$E$2:$E$1515,$D$7,College_Data!$F$2:$F$1515,$D$8)/C39,0) -> 422451.2 | J39: arts | K39: =SUMIFS(College_Data!$G$2:$G$1515,College_Data!$B$2:$B$1515,$J39,College_Data!$C$2:$C$1515,$D$5,College_Data!$D$2:$D$1515,$D$6,College_Data!$E$2:$E$1515,$D$7,College_Data!$F$2:$F$1515,$D$8) -> 1395 | L39: =IFERROR(SUMIFS(College_Data!$K$2:$K$1515,College_Data!$B$2:$B$1515,$J39,College_Data!$C$2:$C$1515,$D$5,College_Data!$D$2:$D$1515,$D$6,College_Data!$E$2:$E$1515,$D$7,College_Data!$F$2:$F$1515,$D$8)/K39,0) -> -39821.147 | M39: =IFERROR(SUMIFS(College_Data!$L$2:$L$1515,College_Data!$B$2:$B$1515,$J39,College_Data!$C$2:$C$1515,$D$5,College_Data!$D$2:$D$1515,$D$6,College_Data!$E$2:$E$1515,$D$7,College_Data!$F$2:$F$1515,$D$8)/K39,0) -> 0.11111111
B40: mid_tier | C40: =SUMIFS(College_Data!$G$2:$G$1515,College_Data!$C$2:$C$1515,$B40,College_Data!$B$2:$B$1515,$D$4,College_Data!$D$2:$D$1515,$D$6,College_Data!$E$2:$E$1515,$D$7,College_Data!$F$2:$F$1515,$D$8) -> 10258 | D40: =IFERROR(SUMIFS(College_Data!$K$2:$K$1515,College_Data!$C$2:$C$1515,$B40,College_Data!$B$2:$B$1515,$D$4,College_Data!$D$2:$D$1515,$D$6,College_Data!$E$2:$E$1515,$D$7,College_Data!$F$2:$F$1515,$D$8)/C40,0) -> 278175.23 | E40: =IFERROR(SUMIFS(College_Data!$L$2:$L$1515,College_Data!$C$2:$C$1515,$B40,College_Data!$B$2:$B$1515,$D$4,College_Data!$D$2:$D$1515,$D$6,College_Data!$E$2:$E$1515,$D$7,College_Data!$F$2:$F$1515,$D$8)/C40,0) -> 0.85260285 | F40: =IFERROR(SUMIFS(College_Data!$H$2:$H$1515,College_Data!$C$2:$C$1515,$B40,College_Data!$B$2:$B$1515,$D$4,College_Data!$D$2:$D$1515,$D$6,College_Data!$E$2:$E$1515,$D$7,College_Data!$F$2:$F$1515,$D$8)/C40,0) -> 84645.672 | G40: =IFERROR(SUMIFS(College_Data!$I$2:$I$1515,College_Data!$C$2:$C$1515,$B40,College_Data!$B$2:$B$1515,$D$4,College_Data!$D$2:$D$1515,$D$6,College_Data!$E$2:$E$1515,$D$7,College_Data!$F$2:$F$1515,$D$8)/C40,0) -> 36543.819 | H40: =IFERROR(SUMIFS(College_Data!$J$2:$J$1515,College_Data!$C$2:$C$1515,$B40,College_Data!$B$2:$B$1515,$D$4,College_Data!$D$2:$D$1515,$D$6,College_Data!$E$2:$E$1515,$D$7,College_Data!$F$2:$F$1515,$D$8)/C40,0) -> 362820.31 | J40: business | K40: =SUMIFS(College_Data!$G$2:$G$1515,College_Data!$B$2:$B$1515,$J40,College_Data!$C$2:$C$1515,$D$5,College_Data!$D$2:$D$1515,$D$6,College_Data!$E$2:$E$1515,$D$7,College_Data!$F$2:$F$1515,$D$8) -> 8361 | L40: =IFERROR(SUMIFS(College_Data!$K$2:$K$1515,College_Data!$B$2:$B$1515,$J40,College_Data!$C$2:$C$1515,$D$5,College_Data!$D$2:$D$1515,$D$6,College_Data!$E$2:$E$1515,$D$7,College_Data!$F$2:$F$1515,$D$8)/K40,0) -> 346099.37 | M40: =IFERROR(SUMIFS(College_Data!$L$2:$L$1515,College_Data!$B$2:$B$1515,$J40,College_Data!$C$2:$C$1515,$D$5,College_Data!$D$2:$D$1515,$D$6,College_Data!$E$2:$E$1515,$D$7,College_Data!$F$2:$F$1515,$D$8)/K40,0) -> 0.98433202
B41: regional | C41: =SUMIFS(College_Data!$G$2:$G$1515,College_Data!$C$2:$C$1515,$B41,College_Data!$B$2:$B$1515,$D$4,College_Data!$D$2:$D$1515,$D$6,College_Data!$E$2:$E$1515,$D$7,College_Data!$F$2:$F$1515,$D$8) -> 9060 | D41: =IFERROR(SUMIFS(College_Data!$K$2:$K$1515,College_Data!$C$2:$C$1515,$B41,College_Data!$B$2:$B$1515,$D$4,College_Data!$D$2:$D$1515,$D$6,College_Data!$E$2:$E$1515,$D$7,College_Data!$F$2:$F$1515,$D$8)/C41,0) -> 244432.73 | E41: =IFERROR(SUMIFS(College_Data!$L$2:$L$1515,College_Data!$C$2:$C$1515,$B41,College_Data!$B$2:$B$1515,$D$4,College_Data!$D$2:$D$1515,$D$6,College_Data!$E$2:$E$1515,$D$7,College_Data!$F$2:$F$1515,$D$8)/C41,0) -> 0.87483444 | F41: =IFERROR(SUMIFS(College_Data!$H$2:$H$1515,College_Data!$C$2:$C$1515,$B41,College_Data!$B$2:$B$1515,$D$4,College_Data!$D$2:$D$1515,$D$6,College_Data!$E$2:$E$1515,$D$7,College_Data!$F$2:$F$1515,$D$8)/C41,0) -> 65321.711 | G41: =IFERROR(SUMIFS(College_Data!$I$2:$I$1515,College_Data!$C$2:$C$1515,$B41,College_Data!$B$2:$B$1515,$D$4,College_Data!$D$2:$D$1515,$D$6,College_Data!$E$2:$E$1515,$D$7,College_Data!$F$2:$F$1515,$D$8)/C41,0) -> 28602.163 | H41: =IFERROR(SUMIFS(College_Data!$J$2:$J$1515,College_Data!$C$2:$C$1515,$B41,College_Data!$B$2:$B$1515,$D$4,College_Data!$D$2:$D$1515,$D$6,College_Data!$E$2:$E$1515,$D$7,College_Data!$F$2:$F$1515,$D$8)/C41,0) -> 309754.7 | J41: education | K41: =SUMIFS(College_Data!$G$2:$G$1515,College_Data!$B$2:$B$1515,$J41,College_Data!$C$2:$C$1515,$D$5,College_Data!$D$2:$D$1515,$D$6,College_Data!$E$2:$E$1515,$D$7,College_Data!$F$2:$F$1515,$D$8) -> 1352 | L41: =IFERROR(SUMIFS(College_Data!$K$2:$K$1515,College_Data!$B$2:$B$1515,$J41,College_Data!$C$2:$C$1515,$D$5,College_Data!$D$2:$D$1515,$D$6,College_Data!$E$2:$E$1515,$D$7,College_Data!$F$2:$F$1515,$D$8)/K41,0) -> 11547.855 | M41: =IFERROR(SUMIFS(College_Data!$L$2:$L$1515,College_Data!$B$2:$B$1515,$J41,College_Data!$C$2:$C$1515,$D$5,College_Data!$D$2:$D$1515,$D$6,College_Data!$E$2:$E$1515,$D$7,College_Data!$F$2:$F$1515,$D$8)/K41,0) -> 0.58136095
B42: for_profit | C42: =SUMIFS(College_Data!$G$2:$G$1515,College_Data!$C$2:$C$1515,$B42,College_Data!$B$2:$B$1515,$D$4,College_Data!$D$2:$D$1515,$D$6,College_Data!$E$2:$E$1515,$D$7,College_Data!$F$2:$F$1515,$D$8) -> 2934 | D42: =IFERROR(SUMIFS(College_Data!$K$2:$K$1515,College_Data!$C$2:$C$1515,$B42,College_Data!$B$2:$B$1515,$D$4,College_Data!$D$2:$D$1515,$D$6,College_Data!$E$2:$E$1515,$D$7,College_Data!$F$2:$F$1515,$D$8)/C42,0) -> 102769.67 | E42: =IFERROR(SUMIFS(College_Data!$L$2:$L$1515,College_Data!$C$2:$C$1515,$B42,College_Data!$B$2:$B$1515,$D$4,College_Data!$D$2:$D$1515,$D$6,College_Data!$E$2:$E$1515,$D$7,College_Data!$F$2:$F$1515,$D$8)/C42,0) -> 0.63156101 | F42: =IFERROR(SUMIFS(College_Data!$H$2:$H$1515,College_Data!$C$2:$C$1515,$B42,College_Data!$B$2:$B$1515,$D$4,College_Data!$D$2:$D$1515,$D$6,College_Data!$E$2:$E$1515,$D$7,College_Data!$F$2:$F$1515,$D$8)/C42,0) -> 119694.92 | G42: =IFERROR(SUMIFS(College_Data!$I$2:$I$1515,College_Data!$C$2:$C$1515,$B42,College_Data!$B$2:$B$1515,$D$4,College_Data!$D$2:$D$1515,$D$6,College_Data!$E$2:$E$1515,$D$7,College_Data!$F$2:$F$1515,$D$8)/C42,0) -> 51477.88 | H42: =IFERROR(SUMIFS(College_Data!$J$2:$J$1515,College_Data!$C$2:$C$1515,$B42,College_Data!$B$2:$B$1515,$D$4,College_Data!$D$2:$D$1515,$D$6,College_Data!$E$2:$E$1515,$D$7,College_Data!$F$2:$F$1515,$D$8)/C42,0) -> 222465.34 | J42: health | K42: =SUMIFS(College_Data!$G$2:$G$1515,College_Data!$B$2:$B$1515,$J42,College_Data!$C$2:$C$1515,$D$5,College_Data!$D$2:$D$1515,$D$6,College_Data!$E$2:$E$1515,$D$7,College_Data!$F$2:$F$1515,$D$8) -> 1589 | L42: =IFERROR(SUMIFS(College_Data!$K$2:$K$1515,College_Data!$B$2:$B$1515,$J42,College_Data!$C$2:$C$1515,$D$5,College_Data!$D$2:$D$1515,$D$6,College_Data!$E$2:$E$1515,$D$7,College_Data!$F$2:$F$1515,$D$8)/K42,0) -> 350828.82 | M42: =IFERROR(SUMIFS(College_Data!$L$2:$L$1515,College_Data!$B$2:$B$1515,$J42,College_Data!$C$2:$C$1515,$D$5,College_Data!$D$2:$D$1515,$D$6,College_Data!$E$2:$E$1515,$D$7,College_Data!$F$2:$F$1515,$D$8)/K42,0) -> 0.99181875
J43: humanities | K43: =SUMIFS(College_Data!$G$2:$G$1515,College_Data!$B$2:$B$1515,$J43,College_Data!$C$2:$C$1515,$D$5,College_Data!$D$2:$D$1515,$D$6,College_Data!$E$2:$E$1515,$D$7,College_Data!$F$2:$F$1515,$D$8) -> 1410 | L43: =IFERROR(SUMIFS(College_Data!$K$2:$K$1515,College_Data!$B$2:$B$1515,$J43,College_Data!$C$2:$C$1515,$D$5,College_Data!$D$2:$D$1515,$D$6,College_Data!$E$2:$E$1515,$D$7,College_Data!$F$2:$F$1515,$D$8)/K43,0) -> -13321.206 | M43: =IFERROR(SUMIFS(College_Data!$L$2:$L$1515,College_Data!$B$2:$B$1515,$J43,College_Data!$C$2:$C$1515,$D$5,College_Data!$D$2:$D$1515,$D$6,College_Data!$E$2:$E$1515,$D$7,College_Data!$F$2:$F$1515,$D$8)/K43,0) -> 0.37588652
J44: social_science | K44: =SUMIFS(College_Data!$G$2:$G$1515,College_Data!$B$2:$B$1515,$J44,College_Data!$C$2:$C$1515,$D$5,College_Data!$D$2:$D$1515,$D$6,College_Data!$E$2:$E$1515,$D$7,College_Data!$F$2:$F$1515,$D$8) -> 5989 | L44: =IFERROR(SUMIFS(College_Data!$K$2:$K$1515,College_Data!$B$2:$B$1515,$J44,College_Data!$C$2:$C$1515,$D$5,College_Data!$D$2:$D$1515,$D$6,College_Data!$E$2:$E$1515,$D$7,College_Data!$F$2:$F$1515,$D$8)/K44,0) -> 31064.017 | M44: =IFERROR(SUMIFS(College_Data!$L$2:$L$1515,College_Data!$B$2:$B$1515,$J44,College_Data!$C$2:$C$1515,$D$5,College_Data!$D$2:$D$1515,$D$6,College_Data!$E$2:$E$1515,$D$7,College_Data!$F$2:$F$1515,$D$8)/K44,0) -> 0.66855902
J81: Internship & on-time graduation (ignores those two filters)
J82: Internship | K82: On time | L82: Graduates | M82: Avg net ROI | N82: Label
J83: No | K83: No | L83: =SUMIFS(College_Data!$G$2:$G$1515,College_Data!$E$2:$E$1515,$J83,College_Data!$F$2:$F$1515,$K83,College_Data!$B$2:$B$1515,$D$4,College_Data!$C$2:$C$1515,$D$5,College_Data!$D$2:$D$1515,$D$6) -> 5374 | M83: =IFERROR(SUMIFS(College_Data!$K$2:$K$1515,College_Data!$E$2:$E$1515,$J83,College_Data!$F$2:$F$1515,$K83,College_Data!$B$2:$B$1515,$D$4,College_Data!$C$2:$C$1515,$D$5,College_Data!$D$2:$D$1515,$D$6)/L83,0) -> 184150.84 | N83: =J83&" / "&K83 -> No / No
B84: Notes: table/chart values respond to the yellow filters. Averages are simple means per graduate; ROI figures are skewed by high earners, so medians would be lower. Internship / on-time flags are Yes/No. | J84: No | K84: Yes | L84: =SUMIFS(College_Data!$G$2:$G$1515,College_Data!$E$2:$E$1515,$J84,College_Data!$F$2:$F$1515,$K84,College_Data!$B$2:$B$1515,$D$4,College_Data!$C$2:$C$1515,$D$5,College_Data!$D$2:$D$1515,$D$6) -> 11544 | M84: =IFERROR(SUMIFS(College_Data!$K$2:$K$1515,College_Data!$E$2:$E$1515,$J84,College_Data!$F$2:$F$1515,$K84,College_Data!$B$2:$B$1515,$D$4,College_Data!$C$2:$C$1515,$D$5,College_Data!$D$2:$D$1515,$D$6)/L84,0) -> 246502.56 | N84: =J84&" / "&K84 -> No / Yes
J85: Yes | K85: No | L85: =SUMIFS(College_Data!$G$2:$G$1515,College_Data!$E$2:$E$1515,$J85,College_Data!$F$2:$F$1515,$K85,College_Data!$B$2:$B$1515,$D$4,College_Data!$C$2:$C$1515,$D$5,College_Data!$D$2:$D$1515,$D$6) -> 4155 | M85: =IFERROR(SUMIFS(College_Data!$K$2:$K$1515,College_Data!$E$2:$E$1515,$J85,College_Data!$F$2:$F$1515,$K85,College_Data!$B$2:$B$1515,$D$4,College_Data!$C$2:$C$1515,$D$5,College_Data!$D$2:$D$1515,$D$6)/L85,0) -> 274605.66 | N85: =J85&" / "&K85 -> Yes / No
J86: Yes | K86: Yes | L86: =SUMIFS(College_Data!$G$2:$G$1515,College_Data!$E$2:$E$1515,$J86,College_Data!$F$2:$F$1515,$K86,College_Data!$B$2:$B$1515,$D$4,College_Data!$C$2:$C$1515,$D$5,College_Data!$D$2:$D$1515,$D$6) -> 8927 | M86: =IFERROR(SUMIFS(College_Data!$K$2:$K$1515,College_Data!$E$2:$E$1515,$J86,College_Data!$F$2:$F$1515,$K86,College_Data!$B$2:$B$1515,$D$4,College_Data!$C$2:$C$1515,$D$5,College_Data!$D$2:$D$1515,$D$6)/L86,0) -> 339349.48 | N86: =J86&" / "&K86 -> Yes / Yes

Sheet AI Dashboard
B1: AI Job Impact Dashboard
B2: 2,000 employees | source: ai_job_impact_cleaned.csv (via AI_Data)
B3: FILTERS (pick from the yellow dropdowns; "All" = no filter) | D3: criteria (helper)
B4: Industry | C4: All | D4: =IF(C4="All","*",C4) -> *
B5: AI adoption | C5: All | D5: =IF(C5="All","*",C5) -> *
B6: Automation risk | C6: All | D6: =IF(C6="All","*",C6) -> *
B7: Remote work | C7: All | D7: =IF(C7="All","*",C7) -> *
B10: EMPLOYEES | C10: % REPLACED | D10: % MODIFIED | E10: AVG SALARY CHANGE | F10: AVG PRODUCTIVITY CHG (%) | G10: AVG SATISFACTION (1-10)
B11: =COUNTIFS(AI_Data!$E$2:$E$2001,$D$4,AI_Data!$H$2:$H$2001,$D$5,AI_Data!$I$2:$I$2001,$D$6,AI_Data!$O$2:$O$2001,$D$7) -> 2000 | C11: =IFERROR(COUNTIFS(AI_Data!$E$2:$E$2001,$D$4,AI_Data!$H$2:$H$2001,$D$5,AI_Data!$I$2:$I$2001,$D$6,AI_Data!$O$2:$O$2001,$D$7,AI_Data!$M$2:$M$2001,"Replaced")/COUNTIFS(AI_Data!$E$2:$E$2001,$D$4,AI_Data!$H$2:$H$2001,$D$5,AI_Data!$I$2:$I$2001,$D$6,AI_Data!$O$2:$O$2001,$D$7),0) -> 0.053 | D11: =IFERROR(COUNTIFS(AI_Data!$E$2:$E$2001,$D$4,AI_Data!$H$2:$H$2001,$D$5,AI_Data!$I$2:$I$2001,$D$6,AI_Data!$O$2:$O$2001,$D$7,AI_Data!$M$2:$M$2001,"Modified")/COUNTIFS(AI_Data!$E$2:$E$2001,$D$4,AI_Data!$H$2:$H$2001,$D$5,AI_Data!$I$2:$I$2001,$D$6,AI_Data!$O$2:$O$2001,$D$7),0) -> 0.4005 | E11: =IFERROR(AVERAGEIFS(AI_Data!$R$2:$R$2001,AI_Data!$E$2:$E$2001,$D$4,AI_Data!$H$2:$H$2001,$D$5,AI_Data!$I$2:$I$2001,$D$6,AI_Data!$O$2:$O$2001,$D$7),0) -> 0.060461437 | F11: =IFERROR(AVERAGEIFS(AI_Data!$Q$2:$Q$2001,AI_Data!$E$2:$E$2001,$D$4,AI_Data!$H$2:$H$2001,$D$5,AI_Data!$I$2:$I$2001,$D$6,AI_Data!$O$2:$O$2001,$D$7),0) -> 9.78582 | G11: =IFERROR(AVERAGEIFS(AI_Data!$P$2:$P$2001,AI_Data!$E$2:$E$2001,$D$4,AI_Data!$H$2:$H$2001,$D$5,AI_Data!$I$2:$I$2001,$D$6,AI_Data!$O$2:$O$2001,$D$7),0) -> 6.0205
B13: Job outcome by AI adoption level
B14: AI adoption | C14: Employees | D14: % Unchanged | E14: % Modified | F14: % Replaced | G14: Avg productivity chg (%) | H14: Avg satisfaction
B15: Low | C15: =COUNTIFS(AI_Data!$E$2:$E$2001,$D$4,AI_Data!$I$2:$I$2001,$D$6,AI_Data!$O$2:$O$2001,$D$7,AI_Data!$H$2:$H$2001,$B15) -> 618 | D15: =IFERROR(COUNTIFS(AI_Data!$E$2:$E$2001,$D$4,AI_Data!$I$2:$I$2001,$D$6,AI_Data!$O$2:$O$2001,$D$7,AI_Data!$H$2:$H$2001,$B15,AI_Data!$M$2:$M$2001,"Unchanged")/COUNTIFS(AI_Data!$E$2:$E$2001,$D$4,AI_Data!$I$2:$I$2001,$D$6,AI_Data!$O$2:$O$2001,$D$7,AI_Data!$H$2:$H$2001,$B15),0) -> 0.64724919 | E15: =IFERROR(COUNTIFS(AI_Data!$E$2:$E$2001,$D$4,AI_Data!$I$2:$I$2001,$D$6,AI_Data!$O$2:$O$2001,$D$7,AI_Data!$H$2:$H$2001,$B15,AI_Data!$M$2:$M$2001,"Modified")/COUNTIFS(AI_Data!$E$2:$E$2001,$D$4,AI_Data!$I$2:$I$2001,$D$6,AI_Data!$O$2:$O$2001,$D$7,AI_Data!$H$2:$H$2001,$B15),0) -> 0.35275081 | F15: =IFERROR(COUNTIFS(AI_Data!$E$2:$E$2001,$D$4,AI_Data!$I$2:$I$2001,$D$6,AI_Data!$O$2:$O$2001,$D$7,AI_Data!$H$2:$H$2001,$B15,AI_Data!$M$2:$M$2001,"Replaced")/COUNTIFS(AI_Data!$E$2:$E$2001,$D$4,AI_Data!$I$2:$I$2001,$D$6,AI_Data!$O$2:$O$2001,$D$7,AI_Data!$H$2:$H$2001,$B15),0) -> 0 | G15: =IFERROR(AVERAGEIFS(AI_Data!$Q$2:$Q$2001,AI_Data!$E$2:$E$2001,$D$4,AI_Data!$I$2:$I$2001,$D$6,AI_Data!$O$2:$O$2001,$D$7,AI_Data!$H$2:$H$2001,$B15),0) -> 8.0312621 | H15: =IFERROR(AVERAGEIFS(AI_Data!$P$2:$P$2001,AI_Data!$E$2:$E$2001,$D$4,AI_Data!$I$2:$I$2001,$D$6,AI_Data!$O$2:$O$2001,$D$7,AI_Data!$H$2:$H$2001,$B15),0) -> 6.0469256
B16: Medium | C16: =COUNTIFS(AI_Data!$E$2:$E$2001,$D$4,AI_Data!$I$2:$I$2001,$D$6,AI_Data!$O$2:$O$2001,$D$7,AI_Data!$H$2:$H$2001,$B16) -> 677 | D16: =IFERROR(COUNTIFS(AI_Data!$E$2:$E$2001,$D$4,AI_Data!$I$2:$I$2001,$D$6,AI_Data!$O$2:$O$2001,$D$7,AI_Data!$H$2:$H$2001,$B16,AI_Data!$M$2:$M$2001,"Unchanged")/COUNTIFS(AI_Data!$E$2:$E$2001,$D$4,AI_Data!$I$2:$I$2001,$D$6,AI_Data!$O$2:$O$2001,$D$7,AI_Data!$H$2:$H$2001,$B16),0) -> 0.68980798 | E16: =IFERROR(COUNTIFS(AI_Data!$E$2:$E$2001,$D$4,AI_Data!$I$2:$I$2001,$D$6,AI_Data!$O$2:$O$2001,$D$7,AI_Data!$H$2:$H$2001,$B16,AI_Data!$M$2:$M$2001,"Modified")/COUNTIFS(AI_Data!$E$2:$E$2001,$D$4,AI_Data!$I$2:$I$2001,$D$6,AI_Data!$O$2:$O$2001,$D$7,AI_Data!$H$2:$H$2001,$B16),0) -> 0.31019202 | F16: =IFERROR(COUNTIFS(AI_Data!$E$2:$E$2001,$D$4,AI_Data!$I$2:$I$2001,$D$6,AI_Data!$O$2:$O$2001,$D$7,AI_Data!$H$2:$H$2001,$B16,AI_Data!$M$2:$M$2001,"Replaced")/COUNTIFS(AI_Data!$E$2:$E$2001,$D$4,AI_Data!$I$2:$I$2001,$D$6,AI_Data!$O$2:$O$2001,$D$7,AI_Data!$H$2:$H$2001,$B16),0) -> 0 | G16: =IFERROR(AVERAGEIFS(AI_Data!$Q$2:$Q$2001,AI_Data!$E$2:$E$2001,$D$4,AI_Data!$I$2:$I$2001,$D$6,AI_Data!$O$2:$O$2001,$D$7,AI_Data!$H$2:$H$2001,$B16),0) -> 10.174579 | H16: =IFERROR(AVERAGEIFS(AI_Data!$P$2:$P$2001,AI_Data!$E$2:$E$2001,$D$4,AI_Data!$I$2:$I$2001,$D$6,AI_Data!$O$2:$O$2001,$D$7,AI_Data!$H$2:$H$2001,$B16),0) -> 5.9867061
B17: High | C17: =COUNTIFS(AI_Data!$E$2:$E$2001,$D$4,AI_Data!$I$2:$I$2001,$D$6,AI_Data!$O$2:$O$2001,$D$7,AI_Data!$H$2:$H$2001,$B17) -> 705 | D17: =IFERROR(COUNTIFS(AI_Data!$E$2:$E$2001,$D$4,AI_Data!$I$2:$I$2001,$D$6,AI_Data!$O$2:$O$2001,$D$7,AI_Data!$H$2:$H$2001,$B17,AI_Data!$M$2:$M$2001,"Unchanged")/COUNTIFS(AI_Data!$E$2:$E$2001,$D$4,AI_Data!$I$2:$I$2001,$D$6,AI_Data!$O$2:$O$2001,$D$7,AI_Data!$H$2:$H$2001,$B17),0) -> 0.32056738 | E17: =IFERROR(COUNTIFS(AI_Data!$E$2:$E$2001,$D$4,AI_Data!$I$2:$I$2001,$D$6,AI_Data!$O$2:$O$2001,$D$7,AI_Data!$H$2:$H$2001,$B17,AI_Data!$M$2:$M$2001,"Modified")/COUNTIFS(AI_Data!$E$2:$E$2001,$D$4,AI_Data!$I$2:$I$2001,$D$6,AI_Data!$O$2:$O$2001,$D$7,AI_Data!$H$2:$H$2001,$B17),0) -> 0.52907801 | F17: =IFERROR(COUNTIFS(AI_Data!$E$2:$E$2001,$D$4,AI_Data!$I$2:$I$2001,$D$6,AI_Data!$O$2:$O$2001,$D$7,AI_Data!$H$2:$H$2001,$B17,AI_Data!$M$2:$M$2001,"Replaced")/COUNTIFS(AI_Data!$E$2:$E$2001,$D$4,AI_Data!$I$2:$I$2001,$D$6,AI_Data!$O$2:$O$2001,$D$7,AI_Data!$H$2:$H$2001,$B17),0) -> 0.15035461 | G17: =IFERROR(AVERAGEIFS(AI_Data!$Q$2:$Q$2001,AI_Data!$E$2:$E$2001,$D$4,AI_Data!$I$2:$I$2001,$D$6,AI_Data!$O$2:$O$2001,$D$7,AI_Data!$H$2:$H$2001,$B17),0) -> 10.950539 | H17: =IFERROR(AVERAGEIFS(AI_Data!$P$2:$P$2001,AI_Data!$E$2:$E$2001,$D$4,AI_Data!$I$2:$I$2001,$D$6,AI_Data!$O$2:$O$2001,$D$7,AI_Data!$H$2:$H$2001,$B17),0) -> 6.0297872
B20: Impact by industry
B21: Industry | C21: Employees | D21: % Replaced | E21: Avg salary before | F21: Avg salary after | G21: Avg salary change | H21: Avg productivity chg (%)
B22: Education | C22: =COUNTIFS(AI_Data!$H$2:$H$2001,$D$5,AI_Data!$I$2:$I$2001,$D$6,AI_Data!$O$2:$O$2001,$D$7,AI_Data!$E$2:$E$2001,$B22) -> 293 | D22: =IFERROR(COUNTIFS(AI_Data!$H$2:$H$2001,$D$5,AI_Data!$I$2:$I$2001,$D$6,AI_Data!$O$2:$O$2001,$D$7,AI_Data!$E$2:$E$2001,$B22,AI_Data!$M$2:$M$2001,"Replaced")/COUNTIFS(AI_Data!$H$2:$H$2001,$D$5,AI_Data!$I$2:$I$2001,$D$6,AI_Data!$O$2:$O$2001,$D$7,AI_Data!$E$2:$E$2001,$B22),0) -> 0.061433447 | E22: =IFERROR(AVERAGEIFS(AI_Data!$K$2:$K$2001,AI_Data!$H$2:$H$2001,$D$5,AI_Data!$I$2:$I$2001,$D$6,AI_Data!$O$2:$O$2001,$D$7,AI_Data!$E$2:$E$2001,$B22),0) -> 73839.208 | F22: =IFERROR(AVERAGEIFS(AI_Data!$L$2:$L$2001,AI_Data!$H$2:$H$2001,$D$5,AI_Data!$I$2:$I$2001,$D$6,AI_Data!$O$2:$O$2001,$D$7,AI_Data!$E$2:$E$2001,$B22),0) -> 78322.737 | G22: =IFERROR(AVERAGEIFS(AI_Data!$R$2:$R$2001,AI_Data!$H$2:$H$2001,$D$5,AI_Data!$I$2:$I$2001,$D$6,AI_Data!$O$2:$O$2001,$D$7,AI_Data!$E$2:$E$2001,$B22),0) -> 0.060632235 | H22: =IFERROR(AVERAGEIFS(AI_Data!$Q$2:$Q$2001,AI_Data!$H$2:$H$2001,$D$5,AI_Data!$I$2:$I$2001,$D$6,AI_Data!$O$2:$O$2001,$D$7,AI_Data!$E$2:$E$2001,$B22),0) -> 10.014505
B23: Finance | C23: =COUNTIFS(AI_Data!$H$2:$H$2001,$D$5,AI_Data!$I$2:$I$2001,$D$6,AI_Data!$O$2:$O$2001,$D$7,AI_Data!$E$2:$E$2001,$B23) -> 300 | D23: =IFERROR(COUNTIFS(AI_Data!$H$2:$H$2001,$D$5,AI_Data!$I$2:$I$2001,$D$6,AI_Data!$O$2:$O$2001,$D$7,AI_Data!$E$2:$E$2001,$B23,AI_Data!$M$2:$M$2001,"Replaced")/COUNTIFS(AI_Data!$H$2:$H$2001,$D$5,AI_Data!$I$2:$I$2001,$D$6,AI_Data!$O$2:$O$2001,$D$7,AI_Data!$E$2:$E$2001,$B23),0) -> 0.06 | E23: =IFERROR(AVERAGEIFS(AI_Data!$K$2:$K$2001,AI_Data!$H$2:$H$2001,$D$5,AI_Data!$I$2:$I$2001,$D$6,AI_Data!$O$2:$O$2001,$D$7,AI_Data!$E$2:$E$2001,$B23),0) -> 72531.703 | F23: =IFERROR(AVERAGEIFS(AI_Data!$L$2:$L$2001,AI_Data!$H$2:$H$2001,$D$5,AI_Data!$I$2:$I$2001,$D$6,AI_Data!$O$2:$O$2001,$D$7,AI_Data!$E$2:$E$2001,$B23),0) -> 76106.433 | G23: =IFERROR(AVERAGEIFS(AI_Data!$R$2:$R$2001,AI_Data!$H$2:$H$2001,$D$5,AI_Data!$I$2:$I$2001,$D$6,AI_Data!$O$2:$O$2001,$D$7,AI_Data!$E$2:$E$2001,$B23),0) -> 0.052330652 | H23: =IFERROR(AVERAGEIFS(AI_Data!$Q$2:$Q$2001,AI_Data!$H$2:$H$2001,$D$5,AI_Data!$I$2:$I$2001,$D$6,AI_Data!$O$2:$O$2001,$D$7,AI_Data!$E$2:$E$2001,$B23),0) -> 9.5657667
B24: Healthcare | C24: =COUNTIFS(AI_Data!$H$2:$H$2001,$D$5,AI_Data!$I$2:$I$2001,$D$6,AI_Data!$O$2:$O$2001,$D$7,AI_Data!$E$2:$E$2001,$B24) -> 270 | D24: =IFERROR(COUNTIFS(AI_Data!$H$2:$H$2001,$D$5,AI_Data!$I$2:$I$2001,$D$6,AI_Data!$O$2:$O$2001,$D$7,AI_Data!$E$2:$E$2001,$B24,AI_Data!$M$2:$M$2001,"Replaced")/COUNTIFS(AI_Data!$H$2:$H$2001,$D$5,AI_Data!$I$2:$I$2001,$D$6,AI_Data!$O$2:$O$2001,$D$7,AI_Data!$E$2:$E$2001,$B24),0) -> 0.040740741 | E24: =IFERROR(AVERAGEIFS(AI_Data!$K$2:$K$2001,AI_Data!$H$2:$H$2001,$D$5,AI_Data!$I$2:$I$2001,$D$6,AI_Data!$O$2:$O$2001,$D$7,AI_Data!$E$2:$E$2001,$B24),0) -> 73128.737 | F24: =IFERROR(AVERAGEIFS(AI_Data!$L$2:$L$2001,AI_Data!$H$2:$H$2001,$D$5,AI_Data!$I$2:$I$2001,$D$6,AI_Data!$O$2:$O$2001,$D$7,AI_Data!$E$2:$E$2001,$B24),0) -> 78702.03 | G24: =IFERROR(AVERAGEIFS(AI_Data!$R$2:$R$2001,AI_Data!$H$2:$H$2001,$D$5,AI_Data!$I$2:$I$2001,$D$6,AI_Data!$O$2:$O$2001,$D$7,AI_Data!$E$2:$E$2001,$B24),0) -> 0.075916612 | H24: =IFERROR(AVERAGEIFS(AI_Data!$Q$2:$Q$2001,AI_Data!$H$2:$H$2001,$D$5,AI_Data!$I$2:$I$2001,$D$6,AI_Data!$O$2:$O$2001,$D$7,AI_Data!$E$2:$E$2001,$B24),0) -> 9.3072593
B25: IT | C25: =COUNTIFS(AI_Data!$H$2:$H$2001,$D$5,AI_Data!$I$2:$I$2001,$D$6,AI_Data!$O$2:$O$2001,$D$7,AI_Data!$E$2:$E$2001,$B25) -> 298 | D25: =IFERROR(COUNTIFS(AI_Data!$H$2:$H$2001,$D$5,AI_Data!$I$2:$I$2001,$D$6,AI_Data!$O$2:$O$2001,$D$7,AI_Data!$E$2:$E$2001,$B25,AI_Data!$M$2:$M$2001,"Replaced")/COUNTIFS(AI_Data!$H$2:$H$2001,$D$5,AI_Data!$I$2:$I$2001,$D$6,AI_Data!$O$2:$O$2001,$D$7,AI_Data!$E$2:$E$2001,$B25),0) -> 0.053691275 | E25: =IFERROR(AVERAGEIFS(AI_Data!$K$2:$K$2001,AI_Data!$H$2:$H$2001,$D$5,AI_Data!$I$2:$I$2001,$D$6,AI_Data!$O$2:$O$2001,$D$7,AI_Data!$E$2:$E$2001,$B25),0) -> 74847.379 | F25: =IFERROR(AVERAGEIFS(AI_Data!$L$2:$L$2001,AI_Data!$H$2:$H$2001,$D$5,AI_Data!$I$2:$I$2001,$D$6,AI_Data!$O$2:$O$2001,$D$7,AI_Data!$E$2:$E$2001,$B25),0) -> 79551.597 | G25: =IFERROR(AVERAGEIFS(AI_Data!$R$2:$R$2001,AI_Data!$H$2:$H$2001,$D$5,AI_Data!$I$2:$I$2001,$D$6,AI_Data!$O$2:$O$2001,$D$7,AI_Data!$E$2:$E$2001,$B25),0) -> 0.062257643 | H25: =IFERROR(AVERAGEIFS(AI_Data!$Q$2:$Q$2001,AI_Data!$H$2:$H$2001,$D$5,AI_Data!$I$2:$I$2001,$D$6,AI_Data!$O$2:$O$2001,$D$7,AI_Data!$E$2:$E$2001,$B25),0) -> 9.0610738
B26: Manufacturing | C26: =COUNTIFS(AI_Data!$H$2:$H$2001,$D$5,AI_Data!$I$2:$I$2001,$D$6,AI_Data!$O$2:$O$2001,$D$7,AI_Data!$E$2:$E$2001,$B26) -> 295 | D26: =IFERROR(COUNTIFS(AI_Data!$H$2:$H$2001,$D$5,AI_Data!$I$2:$I$2001,$D$6,AI_Data!$O$2:$O$2001,$D$7,AI_Data!$E$2:$E$2001,$B26,AI_Data!$M$2:$M$2001,"Replaced")/COUNTIFS(AI_Data!$H$2:$H$2001,$D$5,AI_Data!$I$2:$I$2001,$D$6,AI_Data!$O$2:$O$2001,$D$7,AI_Data!$E$2:$E$2001,$B26),0) -> 0.037288136 | E26: =IFERROR(AVERAGEIFS(AI_Data!$K$2:$K$2001,AI_Data!$H$2:$H$2001,$D$5,AI_Data!$I$2:$I$2001,$D$6,AI_Data!$O$2:$O$2001,$D$7,AI_Data!$E$2:$E$2001,$B26),0) -> 74792.295 | F26: =IFERROR(AVERAGEIFS(AI_Data!$L$2:$L$2001,AI_Data!$H$2:$H$2001,$D$5,AI_Data!$I$2:$I$2001,$D$6,AI_Data!$O$2:$O$2001,$D$7,AI_Data!$E$2:$E$2001,$B26),0) -> 78489.939 | G26: =IFERROR(AVERAGEIFS(AI_Data!$R$2:$R$2001,AI_Data!$H$2:$H$2001,$D$5,AI_Data!$I$2:$I$2001,$D$6,AI_Data!$O$2:$O$2001,$D$7,AI_Data!$E$2:$E$2001,$B26),0) -> 0.046966609 | H26: =IFERROR(AVERAGEIFS(AI_Data!$Q$2:$Q$2001,AI_Data!$H$2:$H$2001,$D$5,AI_Data!$I$2:$I$2001,$D$6,AI_Data!$O$2:$O$2001,$D$7,AI_Data!$E$2:$E$2001,$B26),0) -> 10.69739
B27: Marketing | C27: =COUNTIFS(AI_Data!$H$2:$H$2001,$D$5,AI_Data!$I$2:$I$2001,$D$6,AI_Data!$O$2:$O$2001,$D$7,AI_Data!$E$2:$E$2001,$B27) -> 273 | D27: =IFERROR(COUNTIFS(AI_Data!$H$2:$H$2001,$D$5,AI_Data!$I$2:$I$2001,$D$6,AI_Data!$O$2:$O$2001,$D$7,AI_Data!$E$2:$E$2001,$B27,AI_Data!$M$2:$M$2001,"Replaced")/COUNTIFS(AI_Data!$H$2:$H$2001,$D$5,AI_Data!$I$2:$I$2001,$D$6,AI_Data!$O$2:$O$2001,$D$7,AI_Data!$E$2:$E$2001,$B27),0) -> 0.06959707 | E27: =IFERROR(AVERAGEIFS(AI_Data!$K$2:$K$2001,AI_Data!$H$2:$H$2001,$D$5,AI_Data!$I$2:$I$2001,$D$6,AI_Data!$O$2:$O$2001,$D$7,AI_Data!$E$2:$E$2001,$B27),0) -> 73196.498 | F27: =IFERROR(AVERAGEIFS(AI_Data!$L$2:$L$2001,AI_Data!$H$2:$H$2001,$D$5,AI_Data!$I$2:$I$2001,$D$6,AI_Data!$O$2:$O$2001,$D$7,AI_Data!$E$2:$E$2001,$B27),0) -> 77597.729 | G27: =IFERROR(AVERAGEIFS(AI_Data!$R$2:$R$2001,AI_Data!$H$2:$H$2001,$D$5,AI_Data!$I$2:$I$2001,$D$6,AI_Data!$O$2:$O$2001,$D$7,AI_Data!$E$2:$E$2001,$B27),0) -> 0.060802512 | H27: =IFERROR(AVERAGEIFS(AI_Data!$Q$2:$Q$2001,AI_Data!$H$2:$H$2001,$D$5,AI_Data!$I$2:$I$2001,$D$6,AI_Data!$O$2:$O$2001,$D$7,AI_Data!$E$2:$E$2001,$B27),0) -> 10.332527
B28: Retail | C28: =COUNTIFS(AI_Data!$H$2:$H$2001,$D$5,AI_Data!$I$2:$I$2001,$D$6,AI_Data!$O$2:$O$2001,$D$7,AI_Data!$E$2:$E$2001,$B28) -> 271 | D28: =IFERROR(COUNTIFS(AI_Data!$H$2:$H$2001,$D$5,AI_Data!$I$2:$I$2001,$D$6,AI_Data!$O$2:$O$2001,$D$7,AI_Data!$E$2:$E$2001,$B28,AI_Data!$M$2:$M$2001,"Replaced")/COUNTIFS(AI_Data!$H$2:$H$2001,$D$5,AI_Data!$I$2:$I$2001,$D$6,AI_Data!$O$2:$O$2001,$D$7,AI_Data!$E$2:$E$2001,$B28),0) -> 0.04797048 | E28: =IFERROR(AVERAGEIFS(AI_Data!$K$2:$K$2001,AI_Data!$H$2:$H$2001,$D$5,AI_Data!$I$2:$I$2001,$D$6,AI_Data!$O$2:$O$2001,$D$7,AI_Data!$E$2:$E$2001,$B28),0) -> 75254.97 | F28: =IFERROR(AVERAGEIFS(AI_Data!$L$2:$L$2001,AI_Data!$H$2:$H$2001,$D$5,AI_Data!$I$2:$I$2001,$D$6,AI_Data!$O$2:$O$2001,$D$7,AI_Data!$E$2:$E$2001,$B28),0) -> 80376.963 | G28: =IFERROR(AVERAGEIFS(AI_Data!$R$2:$R$2001,AI_Data!$H$2:$H$2001,$D$5,AI_Data!$I$2:$I$2001,$D$6,AI_Data!$O$2:$O$2001,$D$7,AI_Data!$E$2:$E$2001,$B28),0) -> 0.066250688 | H28: =IFERROR(AVERAGEIFS(AI_Data!$Q$2:$Q$2001,AI_Data!$H$2:$H$2001,$D$5,AI_Data!$I$2:$I$2001,$D$6,AI_Data!$O$2:$O$2001,$D$7,AI_Data!$E$2:$E$2001,$B28),0) -> 9.5128782
B30: Job outcome by automation risk
B31: Automation risk | C31: Employees | D31: % Unchanged | E31: % Modified | F31: % Replaced
B32: Low | C32: =COUNTIFS(AI_Data!$E$2:$E$2001,$D$4,AI_Data!$H$2:$H$2001,$D$5,AI_Data!$O$2:$O$2001,$D$7,AI_Data!$I$2:$I$2001,$B32) -> 650 | D32: =IFERROR(COUNTIFS(AI_Data!$E$2:$E$2001,$D$4,AI_Data!$H$2:$H$2001,$D$5,AI_Data!$O$2:$O$2001,$D$7,AI_Data!$I$2:$I$2001,$B32,AI_Data!$M$2:$M$2001,"Unchanged")/COUNTIFS(AI_Data!$E$2:$E$2001,$D$4,AI_Data!$H$2:$H$2001,$D$5,AI_Data!$O$2:$O$2001,$D$7,AI_Data!$I$2:$I$2001,$B32),0) -> 1 | E32: =IFERROR(COUNTIFS(AI_Data!$E$2:$E$2001,$D$4,AI_Data!$H$2:$H$2001,$D$5,AI_Data!$O$2:$O$2001,$D$7,AI_Data!$I$2:$I$2001,$B32,AI_Data!$M$2:$M$2001,"Modified")/COUNTIFS(AI_Data!$E$2:$E$2001,$D$4,AI_Data!$H$2:$H$2001,$D$5,AI_Data!$O$2:$O$2001,$D$7,AI_Data!$I$2:$I$2001,$B32),0) -> 0 | F32: =IFERROR(COUNTIFS(AI_Data!$E$2:$E$2001,$D$4,AI_Data!$H$2:$H$2001,$D$5,AI_Data!$O$2:$O$2001,$D$7,AI_Data!$I$2:$I$2001,$B32,AI_Data!$M$2:$M$2001,"Replaced")/COUNTIFS(AI_Data!$E$2:$E$2001,$D$4,AI_Data!$H$2:$H$2001,$D$5,AI_Data!$O$2:$O$2001,$D$7,AI_Data!$I$2:$I$2001,$B32),0) -> 0
B33: Medium | C33: =COUNTIFS(AI_Data!$E$2:$E$2001,$D$4,AI_Data!$H$2:$H$2001,$D$5,AI_Data!$O$2:$O$2001,$D$7,AI_Data!$I$2:$I$2001,$B33) -> 668 | D33: =IFERROR(COUNTIFS(AI_Data!$E$2:$E$2001,$D$4,AI_Data!$H$2:$H$2001,$D$5,AI_Data!$O$2:$O$2001,$D$7,AI_Data!$I$2:$I$2001,$B33,AI_Data!$M$2:$M$2001,"Unchanged")/COUNTIFS(AI_Data!$E$2:$E$2001,$D$4,AI_Data!$H$2:$H$2001,$D$5,AI_Data!$O$2:$O$2001,$D$7,AI_Data!$I$2:$I$2001,$B33),0) -> 0 | E33: =IFERROR(COUNTIFS(AI_Data!$E$2:$E$2001,$D$4,AI_Data!$H$2:$H$2001,$D$5,AI_Data!$O$2:$O$2001,$D$7,AI_Data!$I$2:$I$2001,$B33,AI_Data!$M$2:$M$2001,"Modified")/COUNTIFS(AI_Data!$E$2:$E$2001,$D$4,AI_Data!$H$2:$H$2001,$D$5,AI_Data!$O$2:$O$2001,$D$7,AI_Data!$I$2:$I$2001,$B33),0) -> 1 | F33: =IFERROR(COUNTIFS(AI_Data!$E$2:$E$2001,$D$4,AI_Data!$H$2:$H$2001,$D$5,AI_Data!$O$2:$O$2001,$D$7,AI_Data!$I$2:$I$2001,$B33,AI_Data!$M$2:$M$2001,"Replaced")/COUNTIFS(AI_Data!$E$2:$E$2001,$D$4,AI_Data!$H$2:$H$2001,$D$5,AI_Data!$O$2:$O$2001,$D$7,AI_Data!$I$2:$I$2001,$B33),0) -> 0
B34: High | C34: =COUNTIFS(AI_Data!$E$2:$E$2001,$D$4,AI_Data!$H$2:$H$2001,$D$5,AI_Data!$O$2:$O$2001,$D$7,AI_Data!$I$2:$I$2001,$B34) -> 682 | D34: =IFERROR(COUNTIFS(AI_Data!$E$2:$E$2001,$D$4,AI_Data!$H$2:$H$2001,$D$5,AI_Data!$O$2:$O$2001,$D$7,AI_Data!$I$2:$I$2001,$B34,AI_Data!$M$2:$M$2001,"Unchanged")/COUNTIFS(AI_Data!$E$2:$E$2001,$D$4,AI_Data!$H$2:$H$2001,$D$5,AI_Data!$O$2:$O$2001,$D$7,AI_Data!$I$2:$I$2001,$B34),0) -> 0.64956012 | E34: =IFERROR(COUNTIFS(AI_Data!$E$2:$E$2001,$D$4,AI_Data!$H$2:$H$2001,$D$5,AI_Data!$O$2:$O$2001,$D$7,AI_Data!$I$2:$I$2001,$B34,AI_Data!$M$2:$M$2001,"Modified")/COUNTIFS(AI_Data!$E$2:$E$2001,$D$4,AI_Data!$H$2:$H$2001,$D$5,AI_Data!$O$2:$O$2001,$D$7,AI_Data!$I$2:$I$2001,$B34),0) -> 0.19501466 | F34: =IFERROR(COUNTIFS(AI_Data!$E$2:$E$2001,$D$4,AI_Data!$H$2:$H$2001,$D$5,AI_Data!$O$2:$O$2001,$D$7,AI_Data!$I$2:$I$2001,$B34,AI_Data!$M$2:$M$2001,"Replaced")/COUNTIFS(AI_Data!$E$2:$E$2001,$D$4,AI_Data!$H$2:$H$2001,$D$5,AI_Data!$O$2:$O$2001,$D$7,AI_Data!$I$2:$I$2001,$B34),0) -> 0.15542522
B73: Notes: Salary change = (after - before) / before, averaged per employee. Tables ignore their own dimension filter so all levels stay visible. Yellow cells are the filters.

Sheet College_Data
A1: major | B1: major_category | C1: institution_tier | D1: region | E1: had_internship | F1: completed_on_time | G1: grads | H1: net_cost_usd_sum | I1: debt_usd_sum | J1: added_earnings_10yr_usd_sum | K1: net_roi_usd_sum | L1: positive_roi_count | M1: high_roi_count | N1: roi_pct_sum | P1: Note: college_major_roi_cleaned.csv (30,000 graduates) summarized by major/category/tier/region/internship/on-time into sums and counts so dashboard formulas stay fast. Internship / on-time flags shown as Yes/No.
A2: biology | B2: STEM | C2: for_profit | D2: midwest | E2: No | F2: No | G2: 6 | H2: 750300 | I2: 362400 | J2: 886800 | K2: 136500 | L2: 4 | M2: 0 | N2: 136.4
A3: biology | B3: STEM | C3: for_profit | D3: midwest | E3: No | F3: Yes | G3: 21 | H3: 2026100 | I3: 816800 | J3: 2983200 | K3: 957100 | L3: 17 | M3: 0 | N3: 1053.2
A4: biology | B4: STEM | C4: for_profit | D4: midwest | E4: Yes | F4: No | G4: 2 | H4: 305300 | I4: 0 | J4: 297500 | K4: -7800 | L4: 1 | M4: 0 | N4: -12.3
A5: biology | B5: STEM | C5: for_profit | D5: midwest | E5: Yes | F5: Yes | G5: 12 | H5: 1207900 | I5: 494300 | J5: 1956000 | K5: 748000 | L5: 10 | M5: 0 | N5: 821.6
A6: biology | B6: STEM | C6: for_profit | D6: northeast | E6: No | F6: No | G6: 17 | H6: 2361700 | I6: 1052200 | J6: 2191500 | K6: -170500 | L6: 6 | M6: 0 | N6: -74.7
A7: biology | B7: STEM | C7: for_profit | D7: northeast | E7: No | F7: Yes | G7: 17 | H7: 1747200 | I7: 870200 | J7: 2320500 | K7: 573300 | L7: 12 | M7: 0 | N7: 608.9
A8: biology | B8: STEM | C8: for_profit | D8: northeast | E8: Yes | F8: No | G8: 1 | H8: 153600 | I8: 72200 | J8: 335600 | K8: 182000 | L8: 1 | M8: 0 | N8: 118.5
A9: biology | B9: STEM | C9: for_profit | D9: northeast | E9: Yes | F9: Yes | G9: 5 | H9: 566400 | I9: 275400 | J9: 618100 | K9: 51800 | L9: 2 | M9: 0 | N9: 44.4
A10: biology | B10: STEM | C10: for_profit | D10: south | E10: No | F10: No | G10: 11 | H10: 1463200 | I10: 852900 | J10: 1574300 | K10: 111100 | L10: 4 | M10: 0 | N10: 115.4
A11: biology | B11: STEM | C11: for_profit | D11: south | E11: No | F11: Yes | G11: 20 | H11: 2073800 | I11: 1060900 | J11: 2785500 | K11: 711400 | L11: 15 | M11: 0 | N11: 707.9
A12: biology | B12: STEM | C12: for_profit | D12: south | E12: Yes | F12: No | G12: 5 | H12: 648800 | I12: 312400 | J12: 659200 | K12: 10300 | L12: 3 | M12: 0 | N12: 51.4
A13: biology | B13: STEM | C13: for_profit | D13: south | E13: Yes | F13: Yes | G13: 12 | H13: 1274700 | I13: 643500 | J13: 1857100 | K13: 582700 | L13: 10 | M13: 0 | N13: 561.3
... A1515: social_work | B1515: social_science | C1515: top_public | D1515: west | E1515: Yes | F1515: Yes | G1515: 15 | H1515: 1304500 | I1515: 606900 | J1515: 1779400 | K1515: 474900 | L1515: 10 | M1515: 0 | N1515: 543.5

Sheet AI_Data
A1: Employee_ID | B1: Age | C1: Gender | D1: Education_Level | E1: Industry | F1: Job_Role | G1: Years_Experience | H1: AI_Adoption_Level | I1: Automation_Risk | J1: Upskilling_Required | K1: Salary_Before_AI | L1: Salary_After_AI | M1: Job_Status | N1: Work_Hours_Per_Week | O1: Remote_Work | P1: Job_Satisfaction | Q1: Productivity_Change_Pct | R1: Salary_Change_Pct | T1: Note: Salary_Change_Pct is a formula = (Salary_After_AI - Salary_Before_AI) / Salary_Before_AI. All other columns are from ai_job_impact_cleaned.csv.
A2: E0001 | B2: 50 | C2: Female | D2: Bachelor | E2: Marketing | F2: Content Creator | G2: 26 | H2: High | I2: High | J2: Yes | K2: 106820 | L2: 95455 | M2: Replaced | N2: 45 | O2: No | P2: 5 | Q2: -10.64 | R2: =(L2-K2)/K2 -> -0.10639393
A3: E0002 | B3: 45 | C3: Male | D3: High School | E3: Manufacturing | F3: Quality Inspector | G3: 19 | H3: Low | I3: Low | J3: Yes | K3: 74131 | L3: 72013 | M3: Unchanged | N3: 36 | O3: Yes | P3: 6 | Q3: 19.05 | R3: =(L3-K3)/K3 -> -0.028571043
A4: E0003 | B4: 51 | C4: Female | D4: Master | E4: IT | F4: DevOps Engineer | G4: 28 | H4: Medium | I4: Medium | J4: Yes | K4: 35311 | L4: 42290 | M4: Modified | N4: 46 | O4: Yes | P4: 3 | Q4: 17.05 | R4: =(L4-K4)/K4 -> 0.19764379
A5: E0004 | B5: 48 | C5: Male | D5: PhD | E5: Education | F5: Teacher | G5: 24 | H5: Medium | I5: Medium | J5: Yes | K5: 114478 | L5: 107820 | M5: Modified | N5: 50 | O5: No | P5: 9 | Q5: -2.47 | R5: =(L5-K5)/K5 -> -0.058159646
A6: E0005 | B6: 24 | C6: Male | D6: Bachelor | E6: Healthcare | F6: Doctor | G6: 0 | H6: High | I6: Medium | J6: No | K6: 33890 | L6: 40945 | M6: Modified | N6: 52 | O6: Yes | P6: 6 | Q6: 7.03 | R6: =(L6-K6)/K6 -> 0.2081735
A7: E0006 | B7: 46 | C7: Male | D7: High School | E7: Healthcare | F7: Technician | G7: 21 | H7: Low | I7: Medium | J7: No | K7: 103969 | L7: 104781 | M7: Modified | N7: 36 | O7: No | P7: 6 | Q7: -19.04 | R7: =(L7-K7)/K7 -> 0.0078100203
A8: E0007 | B8: 49 | C8: Male | D8: PhD | E8: Education | F8: Administrator | G8: 24 | H8: High | I8: Medium | J8: No | K8: 78555 | L8: 86183 | M8: Modified | N8: 48 | O8: Yes | P8: 3 | Q8: -17.94 | R8: =(L8-K8)/K8 -> 0.09710394
A9: E0008 | B9: 57 | C9: Male | D9: Bachelor | E9: Finance | F9: Auditor | G9: 34 | H9: Low | I9: High | J9: No | K9: 99479 | L9: 105776 | M9: Unchanged | N9: 44 | O9: Yes | P9: 6 | Q9: 5.51 | R9: =(L9-K9)/K9 -> 0.063299792
A10: E0009 | B10: 50 | C10: Other | D10: Bachelor | E10: Education | F10: Professor | G10: 27 | H10: Low | I10: High | J10: Yes | K10: 102409 | L10: 104197 | M10: Unchanged | N10: 38 | O10: No | P10: 8 | Q10: 3.71 | R10: =(L10-K10)/K10 -> 0.017459403
A11: E0010 | B11: 52 | C11: Male | D11: High School | E11: Healthcare | F11: Nurse | G11: 27 | H11: High | I11: Low | J11: Yes | K11: 31016 | L11: 42699 | M11: Unchanged | N11: 47 | O11: Yes | P11: 4 | Q11: 30.67 | R11: =(L11-K11)/K11 -> 0.37667655
A12: E0011 | B12: 45 | C12: Female | D12: High School | E12: Retail | F12: Store Manager | G12: 22 | H12: Medium | I12: High | J12: No | K12: 93704 | L12: 92231 | M12: Unchanged | N12: 43 | O12: No | P12: 7 | Q12: 12.56 | R12: =(L12-K12)/K12 -> -0.015719713
A13: E0012 | B13: 36 | C13: Other | D13: Master | E13: Healthcare | F13: Nurse | G13: 10 | H13: High | I13: Low | J13: Yes | K13: 78984 | L13: 109956 | M13: Unchanged | N13: 46 | O13: No | P13: 9 | Q13: 26.33 | R13: =(L13-K13)/K13 -> 0.39213005
... A2001: E2000 | B2001: 23 | C2001: Other | D2001: Master | E2001: Marketing | F2001: SEO Specialist | G2001: 0 | H2001: High | I2001: High | J2001: Yes | K2001: 33830 | L2001: 34809 | M2001: Modified | N2001: 37 | O2001: Yes | P2001: 9 | Q2001: 24.4 | R2001: =(L2001-K2001)/K2001 -> 0.028938812
